mne_nirs/__init__.py
mne_nirs/conftest.py
mne_nirs/fixes.py
mne_nirs/channels/__init__.py
mne_nirs/channels/_channels.py
mne_nirs/channels/_roi.py
mne_nirs/channels/_short.py
mne_nirs/channels/tests/__init__.py
mne_nirs/channels/tests/test_channels.py
mne_nirs/channels/tests/test_roi.py
mne_nirs/channels/tests/test_short.py
mne_nirs/datasets/__init__.py
mne_nirs/datasets/audio_or_visual_speech/__init__.py
mne_nirs/datasets/audio_or_visual_speech/_audio_or_visual_speech.py
mne_nirs/datasets/audio_or_visual_speech/tests/__init__.py
mne_nirs/datasets/audio_or_visual_speech/tests/test_dataset_avspeech.py
mne_nirs/datasets/block_speech_noise/__init__.py
mne_nirs/datasets/block_speech_noise/_block_speech_noise.py
mne_nirs/datasets/block_speech_noise/tests/__init__.py
mne_nirs/datasets/block_speech_noise/tests/test_dataset_block.py
mne_nirs/datasets/camh_kf_fnirs_fingertapping/__init__.py
mne_nirs/datasets/camh_kf_fnirs_fingertapping/camh_kf_fnirs_fingertapping.py
mne_nirs/datasets/fnirs_motor_group/__init__.py
mne_nirs/datasets/fnirs_motor_group/fnirs_motor_group.py
mne_nirs/datasets/fnirs_motor_group/tests/__init__.py
mne_nirs/datasets/fnirs_motor_group/tests/test_dataset_tap.py
mne_nirs/datasets/snirf_with_aux/__init__.py
mne_nirs/datasets/snirf_with_aux/snirf_with_aux.py
mne_nirs/datasets/snirf_with_aux/tests/__init__.py
mne_nirs/datasets/snirf_with_aux/tests/test_dataset_aux.py
mne_nirs/experimental_design/__init__.py
mne_nirs/experimental_design/_experimental_design.py
mne_nirs/experimental_design/tests/__init__.py
mne_nirs/experimental_design/tests/test_experimental_design.py
mne_nirs/io/__init__.py
mne_nirs/io/fold/__init__.py
mne_nirs/io/fold/_fold.py
mne_nirs/io/fold/tests/__init__.py
mne_nirs/io/fold/tests/test_fold.py
mne_nirs/io/fold/tests/data/example.xls
mne_nirs/io/snirf/__init__.py
mne_nirs/io/snirf/_aux.py
mne_nirs/io/snirf/_snirf.py
mne_nirs/io/snirf/tests/__init__.py
mne_nirs/io/snirf/tests/test_snirf.py
mne_nirs/preprocessing/__init__.py
mne_nirs-0.7.3.dist-info/METADATA
mne_nirs-0.7.3.dist-info/WHEEL
mne_nirs-0.7.3.dist-info/licenses/LICENSE
mne_nirs-0.7.3.dist-info/RECORD
