Metadata-Version: 2.4
Name: mne-nirs
Version: 0.7.3
Summary: An MNE compatible package for processing near-infrared spectroscopy data
Project-URL: Homepage, https://mne.tools/mne-nirs/
Project-URL: Download, https://github.com/mne-tools/mne-nirs
Project-URL: Source Code, https://github.com/mne-tools/mne-nirs/
Maintainer-email: Robert Luke <robert.luke@mq.edu.au>
License: BSD-3-Clause
License-File: LICENSE
Keywords: ECoG,EEG,MEG,brain,fNIRS,neuroimaging,neuroscience
Classifier: Intended Audience :: Developers
Classifier: Intended Audience :: Science/Research
Classifier: License :: OSI Approved
Classifier: Operating System :: MacOS
Classifier: Operating System :: Microsoft :: Windows
Classifier: Operating System :: POSIX
Classifier: Operating System :: Unix
Classifier: Programming Language :: Python
Classifier: Programming Language :: Python :: 3
Classifier: Topic :: Scientific/Engineering
Classifier: Topic :: Software Development
Requires-Python: >=3.10
Requires-Dist: h5io>=0.1.7
Requires-Dist: mne>=1.0
Requires-Dist: nilearn>=0.9
Requires-Dist: numpy<3,>=1.11.3
Requires-Dist: scipy>=0.17.1
Requires-Dist: seaborn
Provides-Extra: docs
Requires-Dist: matplotlib; extra == 'docs'
Requires-Dist: numpydoc; extra == 'docs'
Requires-Dist: pydata-sphinx-theme; extra == 'docs'
Requires-Dist: sphinx; extra == 'docs'
Requires-Dist: sphinx-gallery; extra == 'docs'
Provides-Extra: tests
Requires-Dist: pytest; extra == 'tests'
Requires-Dist: pytest-cov; extra == 'tests'
